odoo/addons/hr_holidays_public/README.rst
odoo/addons/hr_holidays_public/__init__.py
odoo/addons/hr_holidays_public/__manifest__.py
odoo/addons/hr_holidays_public/i18n/ar.po
odoo/addons/hr_holidays_public/i18n/de.po
odoo/addons/hr_holidays_public/i18n/es.po
odoo/addons/hr_holidays_public/i18n/fi.po
odoo/addons/hr_holidays_public/i18n/fr.po
odoo/addons/hr_holidays_public/i18n/hr.po
odoo/addons/hr_holidays_public/i18n/hr_HR.po
odoo/addons/hr_holidays_public/i18n/hr_holidays_public.pot
odoo/addons/hr_holidays_public/i18n/it.po
odoo/addons/hr_holidays_public/i18n/nl_NL.po
odoo/addons/hr_holidays_public/i18n/pl.po
odoo/addons/hr_holidays_public/i18n/pt_BR.po
odoo/addons/hr_holidays_public/i18n/ro.po
odoo/addons/hr_holidays_public/i18n/sl.po
odoo/addons/hr_holidays_public/models/__init__.py
odoo/addons/hr_holidays_public/models/hr_holidays.py
odoo/addons/hr_holidays_public/models/hr_holidays_public.py
odoo/addons/hr_holidays_public/models/hr_holidays_status.py
odoo/addons/hr_holidays_public/models/resource.py
odoo/addons/hr_holidays_public/readme/CONFIGURE.rst
odoo/addons/hr_holidays_public/readme/CONTRIBUTORS.rst
odoo/addons/hr_holidays_public/readme/DESCRIPTION.rst
odoo/addons/hr_holidays_public/readme/USAGE.rst
odoo/addons/hr_holidays_public/security/ir.model.access.csv
odoo/addons/hr_holidays_public/static/description/icon.png
odoo/addons/hr_holidays_public/static/description/icon.svg
odoo/addons/hr_holidays_public/static/description/index.html
odoo/addons/hr_holidays_public/tests/__init__.py
odoo/addons/hr_holidays_public/tests/test_holidays_calculation.py
odoo/addons/hr_holidays_public/tests/test_holidays_public.py
odoo/addons/hr_holidays_public/views/hr_holidays_public_view.xml
odoo/addons/hr_holidays_public/views/hr_holidays_status_views.xml
odoo/addons/hr_holidays_public/wizards/__init__.py
odoo/addons/hr_holidays_public/wizards/holidays_public_next_year_wizard.py
odoo11_addon_hr_holidays_public-11.0.1.0.1.dist-info/METADATA
odoo11_addon_hr_holidays_public-11.0.1.0.1.dist-info/RECORD
odoo11_addon_hr_holidays_public-11.0.1.0.1.dist-info/WHEEL
odoo11_addon_hr_holidays_public-11.0.1.0.1.dist-info/top_level.txt
